CHANGELOG.md
HACKING.md
README.md
setup.py
build_scripts/ranger
build_scripts/rifle
doc/colorschemes.md
doc/ranger.1
doc/ranger.desktop
doc/rifle.1
doc/config/commands.py
doc/config/rc.conf
doc/config/rifle.conf
doc/config/scope.sh
doc/config/colorschemes/default.py
doc/config/colorschemes/jungle.py
doc/config/colorschemes/snow.py
doc/tools/convert_papermode_to_metadata.py
doc/tools/performance_test.py
doc/tools/print_colors.py
doc/tools/print_keys.py
examples/README
examples/bash_automatic_cd.sh
examples/bash_subshell_notice.sh
examples/plugin_avfs.py
examples/plugin_chmod_keybindings.py
examples/plugin_fasd_add.py
examples/plugin_file_filter.py
examples/plugin_hello_world.py
examples/plugin_ipc.py
examples/plugin_linemode.py
examples/plugin_new_macro.py
examples/plugin_new_sorting_method.py
examples/plugin_pmount.py
examples/plugin_pmount_dynamic.py
examples/rc_emacs.conf
examples/rifle_different_file_opener.conf
examples/rifle_sxiv.sh
examples/vim_file_chooser.vim
ranger/__init__.py
ranger/api/__init__.py
ranger/api/commands.py
ranger/colorschemes/__init__.py
ranger/colorschemes/default.py
ranger/colorschemes/jungle.py
ranger/colorschemes/snow.py
ranger/colorschemes/solarized.py
ranger/config/__init__.py
ranger/config/commands.py
ranger/config/commands_sample.py
ranger/config/rc.conf
ranger/config/rifle.conf
ranger/container/__init__.py
ranger/container/bookmarks.py
ranger/container/directory.py
ranger/container/file.py
ranger/container/fsobject.py
ranger/container/history.py
ranger/container/settings.py
ranger/container/tags.py
ranger/core/__init__.py
ranger/core/actions.py
ranger/core/filter_stack.py
ranger/core/fm.py
ranger/core/linemode.py
ranger/core/loader.py
ranger/core/main.py
ranger/core/metadata.py
ranger/core/runner.py
ranger/core/shared.py
ranger/core/tab.py
ranger/data/mime.types
ranger/data/scope.sh
ranger/ext/__init__.py
ranger/ext/accumulator.py
ranger/ext/cached_function.py
ranger/ext/curses_interrupt_handler.py
ranger/ext/direction.py
ranger_fm.egg-info/PKG-INFO
ranger_fm.egg-info/SOURCES.txt
ranger_fm.egg-info/dependency_links.txt
ranger_fm.egg-info/top_level.txt