Metadata-Version: 1.1
Name: ranger-fm
Version: 1.9.2
Summary: Vim-like file manager
Home-page: https://ranger.github.io
Author: Roman Zimbelmann
Author-email: hut@hut.pm
License: GPL3
Keywords: file-manager vim console file-launcher file-preview
Platform: UNKNOWN
Classifier: Environment :: Console
Classifier: Environment :: Console :: Curses
Classifier: Intended Audience :: Developers
Classifier: Intended Audience :: End Users/Desktop
Classifier: Intended Audience :: System Administrators
Classifier: License :: OSI Approved :: GNU General Public License v3 (GPLv3)
Classifier: Operating System :: MacOS
Classifier: Operating System :: POSIX
Classifier: Operating System :: Unix
Classifier: Programming Language :: Python :: 2.6
Classifier: Programming Language :: Python :: 2.7
Classifier: Programming Language :: Python :: 3.1
Classifier: Programming Language :: Python :: 3.2
Classifier: Programming Language :: Python :: 3.3
Classifier: Programming Language :: Python :: 3.4
Classifier: Programming Language :: Python :: 3.5
Classifier: Programming Language :: Python :: 3.6
Classifier: Topic :: Desktop Environment :: File Managers
Classifier: Topic :: Utilities
